odoo8_addon_website_event_contact-8.0.1.0.0-py2.7-nspkg.pth
odoo8_addon_website_event_contact-8.0.1.0.0.dist-info/top_level.txt
odoo8_addon_website_event_contact-8.0.1.0.0.dist-info/WHEEL
odoo8_addon_website_event_contact-8.0.1.0.0.dist-info/RECORD
odoo8_addon_website_event_contact-8.0.1.0.0.dist-info/metadata.json
odoo8_addon_website_event_contact-8.0.1.0.0.dist-info/DESCRIPTION.rst
odoo8_addon_website_event_contact-8.0.1.0.0.dist-info/METADATA
odoo8_addon_website_event_contact-8.0.1.0.0.dist-info/namespace_packages.txt
odoo_addons/website_event_contact/__openerp__.py
odoo_addons/website_event_contact/__init__.py
odoo_addons/website_event_contact/README.rst
odoo_addons/website_event_contact/views/website_event_contact.xml
odoo_addons/website_event_contact/static/description/icon.png
